bib2coins
setup.py
bib2coins.egg-info/PKG-INFO
bib2coins.egg-info/SOURCES.txt
bib2coins.egg-info/dependency_links.txt
bib2coins.egg-info/top_level.txt
bibtex/__init__.py
bibtex/bibparse.py