Metadata-Version: 1.1
Name: bib2coins
Version: 0.1
Summary: Module to parse human-style date ranges (eg. 15th-19th March 2011) to datetimes
Home-page: https://github.com/robintw/bib2coins
Author: Robin Wilson
Author-email: robin@rtwilson.com
License: BSD
Platform: UNKNOWN
Classifier: Development Status :: 4 - Beta
Classifier: Intended Audience :: End Users/Desktop
Classifier: Intended Audience :: Science/Research
Classifier: Topic :: Text Editors :: Text Processing
Classifier: Topic :: Text Processing :: Markup :: LaTeX
Classifier: Topic :: Software Development :: Libraries :: Python Modules
Classifier: License :: OSI Approved :: BSD License
Classifier: Programming Language :: Python
